dateslider/__init__.py
dateslider/_version.py
dateslider/traits.py
dateslider/widgets.py
dateslider/__pycache__/__init__.cpython-34.pyc
dateslider/__pycache__/_version.cpython-34.pyc
dateslider/__pycache__/traits.cpython-34.pyc
dateslider/__pycache__/widgets.cpython-34.pyc
dateslider/static/index.js
dateslider-0.0.0.dist-info/DESCRIPTION.rst
dateslider-0.0.0.dist-info/METADATA
dateslider-0.0.0.dist-info/RECORD
dateslider-0.0.0.dist-info/WHEEL
dateslider-0.0.0.dist-info/metadata.json
dateslider-0.0.0.dist-info/top_level.txt
