Metadata-Version: 2.0
Name: dateslider
Version: 0.0.0
Summary: A date slider Jupyter widget
Home-page: https://github.com/bollwyvl/widget-dateslider
Author: Nicholas Bollweg
Author-email: nick.bollweg@gmail.com
License: BSD-3-Clause
Keywords: ipython jupyter blockly
Platform: UNKNOWN
Classifier: Development Status :: 4 - Beta
Classifier: Framework :: IPython
Classifier: Programming Language :: Python
Classifier: License :: OSI Approved :: BSD License
